{
    "last_updated": "2026-07-10 06:48:34",
    "week": "2026-07-06 00:00:00",
    "features": {
        "nb_events": 4217.0,
        "total_mentions": 19079.0,
        "total_articles": 18657.0,
        "avg_goldstein": 0.20253734882617971,
        "min_goldstein": -10.0,
        "avg_tone": -2.1552681908215945,
        "min_tone": -18.9542483660131,
        "tension_score": 33243.6,
        "cooperation_score": 38760.8,
        "verbal_conflict_mentions": 2493.0,
        "material_conflict_mentions": 2830.0,
        "verbal_coop_mentions": 11627.0,
        "material_coop_mentions": 2129.0,
        "major_country_events": 2068.0,
        "major_country_conflict_mentions": 1437.0,
        "usa_conflict_mentions": 1687.0,
        "china_conflict_mentions": 39.0,
        "russia_conflict_mentions": 45.0,
        "middle_east_conflict_mentions": 138.0,
        "usa_china_tension": 0.0,
        "usa_russia_tension": 90.0,
        "conflict_mentions": 5323.0,
        "coop_mentions": 13756.0,
        "conflict_ratio": 0.2789832285115304,
        "material_conflict_ratio": 0.14832285115303984,
        "major_conflict_ratio": 0.07531446540880503,
        "weekly_return_current": -0.03109536322603801,
        "vol_4w": 0.03575987342584216,
        "vol_8w": 0.0707179527717681,
        "vol_12w": 0.08078709020062473,
        "momentum_4w": -0.24917852398211926,
        "momentum_12w": -0.3081348225180174,
        "momentum_26w": 0.175411581112225,
        "drawdown_26w": -0.3901788024328272,
        "vix": 15.569999694824219,
        "vix_delta_1w": -2.0799999237060547,
        "vix_zscore_52w": -0.7242224623410976,
        "nb_events_lag1": 5117.0,
        "nb_events_lag2": 5078.0,
        "nb_events_delta1": -900.0,
        "nb_events_zscore_52w": 0.8663698879476106,
        "total_mentions_lag1": 22329.0,
        "total_mentions_lag2": 23000.0,
        "total_mentions_delta1": -3250.0,
        "total_mentions_zscore_52w": 0.8730492583207655,
        "avg_goldstein_lag1": 0.41407074457690046,
        "avg_goldstein_lag2": 0.3879873966128397,
        "avg_goldstein_delta1": -0.21153339575072075,
        "avg_goldstein_zscore_52w": 0.16071707502045363,
        "avg_tone_lag1": -1.6994994129904153,
        "avg_tone_lag2": -2.073754389656028,
        "avg_tone_delta1": -0.4557687778311792,
        "avg_tone_zscore_52w": -0.16747388956160272,
        "tension_score_lag1": 35159.5,
        "tension_score_lag2": 39057.7,
        "tension_score_delta1": -1915.9000000000015,
        "tension_score_zscore_52w": 0.9834960570309339,
        "cooperation_score_lag1": 45867.2,
        "cooperation_score_lag2": 50352.3,
        "cooperation_score_delta1": -7106.399999999994,
        "cooperation_score_zscore_52w": 0.7884012097332271,
        "material_conflict_mentions_lag1": 2848.0,
        "material_conflict_mentions_lag2": 3460.0,
        "material_conflict_mentions_delta1": -18.0,
        "material_conflict_mentions_zscore_52w": 0.9569469793928329,
        "verbal_conflict_mentions_lag1": 3370.0,
        "verbal_conflict_mentions_lag2": 2982.0,
        "verbal_conflict_mentions_delta1": -877.0,
        "verbal_conflict_mentions_zscore_52w": 0.835953255934028,
        "conflict_ratio_lag1": 0.27845947156291984,
        "conflict_ratio_lag2": 0.28007477935741926,
        "conflict_ratio_delta1": 0.0005237569486105653,
        "conflict_ratio_zscore_52w": -0.4281145321471906,
        "material_conflict_ratio_lag1": 0.12754142409314823,
        "material_conflict_ratio_lag2": 0.15042824225033694,
        "material_conflict_ratio_delta1": 0.02078142705989161,
        "material_conflict_ratio_zscore_52w": -0.24972269369637995,
        "major_conflict_ratio_lag1": 0.07071204657411553,
        "major_conflict_ratio_lag2": 0.0736054954132429,
        "major_conflict_ratio_delta1": 0.004602418834689495,
        "major_conflict_ratio_zscore_52w": -0.06257176070399748,
        "major_country_conflict_mentions_lag1": 1579.0,
        "major_country_conflict_mentions_lag2": 1693.0,
        "major_country_conflict_mentions_delta1": -142.0,
        "major_country_conflict_mentions_zscore_52w": 0.9828509471162438,
        "usa_conflict_mentions_lag1": 1558.0,
        "usa_conflict_mentions_lag2": 1847.0,
        "usa_conflict_mentions_delta1": 129.0,
        "usa_conflict_mentions_zscore_52w": 1.1981315972690938,
        "china_conflict_mentions_lag1": 62.0,
        "china_conflict_mentions_lag2": 36.0,
        "china_conflict_mentions_delta1": -23.0,
        "china_conflict_mentions_zscore_52w": 0.17273495471589298,
        "russia_conflict_mentions_lag1": 117.0,
        "russia_conflict_mentions_lag2": 199.0,
        "russia_conflict_mentions_delta1": -72.0,
        "russia_conflict_mentions_zscore_52w": 0.30866945684253455,
        "middle_east_conflict_mentions_lag1": 254.0,
        "middle_east_conflict_mentions_lag2": 266.0,
        "middle_east_conflict_mentions_delta1": -116.0,
        "middle_east_conflict_mentions_zscore_52w": 0.09537007878074122,
        "usa_china_tension_lag1": 72.0,
        "usa_china_tension_lag2": 82.0,
        "usa_china_tension_delta1": -72.0,
        "usa_china_tension_zscore_52w": -0.5139027356545132,
        "usa_russia_tension_lag1": 50.0,
        "usa_russia_tension_lag2": 0.0,
        "usa_russia_tension_delta1": 40.0,
        "usa_russia_tension_zscore_52w": 3.941046317824837,
        "tension_x_vol_4w": 0.03516969451424103,
        "conflict_x_drawdown": -0.09743650156675325,
        "vix_x_tension": -0.7122699361257034
    },
    "top_events": {
        "Make statement, not specified below": 1582,
        "Make a visit": 1382,
        "Host a visit": 1353,
        "Consult, not specified below": 1184,
        "Praise or endorse": 1179,
        "Appeal, not specified below": 1164,
        "Use conventional military force": 929,
        "Arrest, detain, or charge with legal action": 673,
        "Express intent to meet or negotiate": 636,
        "Engage in negotiation": 553
    },
    "top_conflict_countries": {
        "US": 2554,
        "NI": 254,
        "IR": 200,
        "AS": 196,
        "IS": 146,
        "UK": 145,
        "IN": 131,
        "PK": 87,
        "SF": 85,
        "CH": 80
    },
    "evolution": {
        "tension_score": -5.45,
        "conflict_ratio": 0.19,
        "material_conflict_ratio": 16.29,
        "usa_china_tension": -100.0,
        "usa_russia_tension": 80.0,
        "avg_tone": -26.82,
        "weekly_return_current": 42.84,
        "vol_4w": -18.85,
        "vix": -11.78
    }
}